[
  {
    "MapId": 0,
    "CreatorId": null,
    "CreationDate": null,
    "Points": [
      {
        "X": 136.3,
        "Y": 160.2
      },
      {
        "X": 117.5,
        "Y": 185.5
      },
      {
        "X": 102.1,
        "Y": 223.4
      },
      {
        "X": 117.5,
        "Y": 275.5
      },
      {
        "X": 157.6,
        "Y": 349.11
      },
      {
        "X": 202.1,
        "Y": 367
      },
      {
        "X": 286.7,
        "Y": 367
      },
      {
        "X": 321.7,
        "Y": 353.7
      },
      {
        "X": 349,
        "Y": 322.1
      },
      {
        "X": 371.3,
        "Y": 267.4
      },
      {
        "X": 352.5,
        "Y": 216.2
      },
      {
        "X": 295.3,
        "Y": 198.3
      },
      {
        "X": 242.3,
        "Y": 167.6
      },
      {
        "X": 202.1,
        "Y": 145.4
      },
      {
        "X": 242.3,
        "Y": 367
      },
      {
        "X": 131.1,
        "Y": 318.4
      },
      {
        "X": 171.6,
        "Y": 156
      }
    ]
  },
  {
    "MapId": 1,
    "CreatorId": null,
    "CreationDate": null,
    "Points": [
      {
        "X": 117.5,
        "Y": 116.6
      },
      {
        "X": 117.5,
        "Y": 167.6
      },
      {
        "X": 71.6,
        "Y": 184.4
      },
      {
        "X": 102.1,
        "Y": 221.5
      },
      {
        "X": 71.6,
        "Y": 251.2
      },
      {
        "X": 108.1,
        "Y": 267.4
      },
      {
        "X": 79.8,
        "Y": 306.8
      },
      {
        "X": 122.8,
        "Y": 306.8
      },
      {
        "X": 136.1,
        "Y": 349.1
      },
      {
        "X": 171.6,
        "Y": 342.4
      },
      {
        "X": 208.1,
        "Y": 372.3
      },
      {
        "X": 222.8,
        "Y": 330.2
      },
      {
        "X": 267.3,
        "Y": 349.1
      },
      {
        "X": 271.6,
        "Y": 306.8
      },
      {
        "X": 354.1,
        "Y": 306.8
      },
      {
        "X": 308.1,
        "Y": 259.8
      },
      {
        "X": 331.5,
        "Y": 238
      },
      {
        "X": 288.5,
        "Y": 221.5
      },
      {
        "X": 300,
        "Y": 184.4
      },
      {
        "X": 254.1,
        "Y": 173.3
      },
      {
        "X": 267.3,
        "Y": 125.4
      },
      {
        "X": 217.5,
        "Y": 141.2
      },
      {
        "X": 194,
        "Y": 106.2
      },
      {
        "X": 154.1,
        "Y": 133.2
      }
    ]
  },
  {
    "MapId": 2,
    "CreatorId": null,
    "CreationDate": null,
    "Points": [
      {
        "X": 17.5,
        "Y": 206.4
      },
      {
        "X": 36.1,
        "Y": 173.3
      },
      {
        "X": 79.8,
        "Y": 191.6
      },
      {
        "X": 108.1,
        "Y": 173.3
      },
      {
        "X": 54.1,
        "Y": 238
      },
      {
        "X": 94,
        "Y": 141.2
      },
      {
        "X": 87.8,
        "Y": 415.5
      },
      {
        "X": 136.1,
        "Y": 430.5
      },
      {
        "X": 36.1,
        "Y": 394
      },
      {
        "X": 194,
        "Y": 426.2
      },
      {
        "X": 248,
        "Y": 438.1
      },
      {
        "X": 254.1,
        "Y": 394
      },
      {
        "X": 288.5,
        "Y": 415.5
      },
      {
        "X": 331.5,
        "Y": 426.2
      },
      {
        "X": 367.3,
        "Y": 438.1
      },
      {
        "X": 417.8,
        "Y": 405.4
      },
      {
        "X": 445.2,
        "Y": 405.4
      },
      {
        "X": 336.4,
        "Y": 373.1
      },
      {
        "X": 445.2,
        "Y": 380.9
      },
      {
        "X": 495.5,
        "Y": 254.6
      },
      {
        "X": 254.1,
        "Y": 141.2
      },
      {
        "X": 163.6,
        "Y": 55.6
      },
      {
        "X": 199,
        "Y": 109.2
      },
      {
        "X": 87.8,
        "Y": 87.2
      },
      {
        "X": 43.9,
        "Y": 109.2
      },
      {
        "X": 43.9,
        "Y": 55.6
      },
      {
        "X": 271.3,
        "Y": 75.4
      },
      {
        "X": 382,
        "Y": 92.4
      },
      {
        "X": 317.8,
        "Y": 119.3
      },
      {
        "X": 445.2,
        "Y": 75.4
      },
      {
        "X": 490.1,
        "Y": 114.3
      },
      {
        "X": 456.2,
        "Y": 159.2
      },
      {
        "X": 456.2,
        "Y": 213.1
      },
      {
        "X": 502.1,
        "Y": 206.4
      },
      {
        "X": 502.1,
        "Y": 166.5
      },
      {
        "X": 490.1,
        "Y": 62.3
      },
      {
        "X": 456.2,
        "Y": 114.3
      },
      {
        "X": 402.1,
        "Y": 55.6
      },
      {
        "X": 345.3,
        "Y": 40.8
      },
      {
        "X": 50,
        "Y": 430.5
      },
      {
        "X": 69.9,
        "Y": 373.1
      }
    ]
  },
  {
    "MapId": 3,
    "CreatorId": null,
    "CreationDate": null,
    "Points": [
      {
        "X": 108.1,
        "Y": 213.1
      },
      {
        "X": 136.1,
        "Y": 206.4
      },
      {
        "X": 87.8,
        "Y": 199
      },
      {
        "X": 108.1,
        "Y": 191.6
      },
      {
        "X": 99,
        "Y": 230.1
      },
      {
        "X": 126,
        "Y": 222.3
      },
      {
        "X": 115,
        "Y": 243.2
      },
      {
        "X": 163.6,
        "Y": 373.1
      },
      {
        "X": 150,
        "Y": 373.1
      },
      {
        "X": 132,
        "Y": 357.2
      },
      {
        "X": 263.6,
        "Y": 438.1
      },
      {
        "X": 282,
        "Y": 444.2
      },
      {
        "X": 271.3,
        "Y": 415.5
      },
      {
        "X": 293,
        "Y": 430.5
      },
      {
        "X": 288,
        "Y": 415.5
      },
      {
        "X": 402.1,
        "Y": 444.2
      },
      {
        "X": 490.1,
        "Y": 292
      },
      {
        "X": 471,
        "Y": 305
      },
      {
        "X": 471,
        "Y": 279.7
      },
      {
        "X": 482,
        "Y": 259.8
      },
      {
        "X": 288,
        "Y": 166.5
      },
      {
        "X": 308,
        "Y": 166.5
      },
      {
        "X": 271.3,
        "Y": 186
      },
      {
        "X": 293,
        "Y": 191.6
      },
      {
        "X": 155,
        "Y": 199
      },
      {
        "X": 317.8,
        "Y": 149
      },
      {
        "X": 326,
        "Y": 179
      },
      {
        "X": 308,
        "Y": 191.6
      },
      {
        "X": 314,
        "Y": 125
      },
      {
        "X": 471,
        "Y": 243.2
      },
      {
        "X": 471,
        "Y": 199
      },
      {
        "X": 451,
        "Y": 237
      },
      {
        "X": 456.2,
        "Y": 213.1
      },
      {
        "X": 456.2,
        "Y": 259.8
      },
      {
        "X": 451,
        "Y": 287.3
      },
      {
        "X": 326,
        "Y": 199
      },
      {
        "X": 382,
        "Y": 438.1
      },
      {
        "X": 382,
        "Y": 420
      },
      {
        "X": 308,
        "Y": 415.5
      },
      {
        "X": 150,
        "Y": 349.8
      },
      {
        "X": 171.3,
        "Y": 357.2
      },
      {
        "X": 163.6,
        "Y": 342.4
      },
      {
        "X": 136.1,
        "Y": 336.8
      },
      {
        "X": 155,
        "Y": 329.8
      }
    ]
  },
  {
    "MapId": 4,
    "CreatorId": null,
    "CreationDate": null,
    "Points": [
      {
        "X": 110,
        "Y": 210
      },
      {
        "X": 110,
        "Y": 240
      },
      {
        "X": 110,
        "Y": 270
      },
      {
        "X": 110,
        "Y": 300
      },
      {
        "X": 110,
        "Y": 330
      },
      {
        "X": 110,
        "Y": 360
      },
      {
        "X": 165,
        "Y": 210
      },
      {
        "X": 165,
        "Y": 240
      },
      {
        "X": 165,
        "Y": 270
      },
      {
        "X": 165,
        "Y": 300
      },
      {
        "X": 165,
        "Y": 330
      },
      {
        "X": 165,
        "Y": 360
      },
      {
        "X": 221,
        "Y": 210
      },
      {
        "X": 221,
        "Y": 240
      },
      {
        "X": 221,
        "Y": 270
      },
      {
        "X": 221,
        "Y": 300
      },
      {
        "X": 221,
        "Y": 330
      },
      {
        "X": 221,
        "Y": 360
      },
      {
        "X": 276,
        "Y": 210
      },
      {
        "X": 276,
        "Y": 240
      },
      {
        "X": 276,
        "Y": 270
      },
      {
        "X": 276,
        "Y": 300
      },
      {
        "X": 276,
        "Y": 330
      },
      {
        "X": 276,
        "Y": 360
      },
      {
        "X": 329,
        "Y": 210
      },
      {
        "X": 329,
        "Y": 240
      },
      {
        "X": 329,
        "Y": 270
      },
      {
        "X": 329,
        "Y": 300
      },
      {
        "X": 329,
        "Y": 330
      },
      {
        "X": 329,
        "Y": 360
      },
      {
        "X": 384,
        "Y": 210
      },
      {
        "X": 384,
        "Y": 240
      },
      {
        "X": 384,
        "Y": 270
      },
      {
        "X": 384,
        "Y": 300
      },
      {
        "X": 384,
        "Y": 330
      },
      {
        "X": 384,
        "Y": 360
      }
    ]
  },
  {
    "MapId": 5,
    "CreatorId": null,
    "CreationDate": null,
    "Points": [
      {
        "X": 61.7,
        "Y": 465.7
      },
      {
        "X": 365.6,
        "Y": 419.3
      },
      {
        "X": 226.2,
        "Y": 384.3
      },
      {
        "X": 226.2,
        "Y": 355.9
      },
      {
        "X": 30.7,
        "Y": 268.5
      },
      {
        "X": 50,
        "Y": 259.8
      },
      {
        "X": 44.3,
        "Y": 233.5
      },
      {
        "X": 57.6,
        "Y": 393.5
      },
      {
        "X": 39.6,
        "Y": 384.3
      },
      {
        "X": 50,
        "Y": 368.2
      },
      {
        "X": 69.9,
        "Y": 368.2
      },
      {
        "X": 61.7,
        "Y": 340.7
      },
      {
        "X": 265.6,
        "Y": 189.9
      },
      {
        "X": 265.6,
        "Y": 162.4
      },
      {
        "X": 295.9,
        "Y": 167.1
      },
      {
        "X": 326.2,
        "Y": 167.1
      },
      {
        "X": 342.3,
        "Y": 184.1
      },
      {
        "X": 369.8,
        "Y": 196.4
      },
      {
        "X": 383.1,
        "Y": 176.5
      },
      {
        "X": 365.6,
        "Y": 142.4
      },
      {
        "X": 350.5,
        "Y": 313.2
      },
      {
        "X": 342.3,
        "Y": 347.2
      },
      {
        "X": 369.8,
        "Y": 364.3
      },
      {
        "X": 383.1,
        "Y": 334.9
      },
      {
        "X": 376.5,
        "Y": 300.8
      },
      {
        "X": 418.2,
        "Y": 314.9
      },
      {
        "X": 442.3,
        "Y": 355.9
      },
      {
        "X": 483.1,
        "Y": 372
      },
      {
        "X": 483.1,
        "Y": 340.7
      },
      {
        "X": 457.5,
        "Y": 313.2
      },
      {
        "X": 483.1,
        "Y": 300.8
      },
      {
        "X": 436.7,
        "Y": 276.2
      },
      {
        "X": 471,
        "Y": 268.5
      }
    ]
  }
]